threads_arg_python_bindings.cpython-312-darwin.so
threads_arg-0.2.1.dist-info/RECORD
threads_arg-0.2.1.dist-info/WHEEL
threads_arg-0.2.1.dist-info/entry_points.txt
threads_arg-0.2.1.dist-info/METADATA
threads_arg-0.2.1.dist-info/licenses/LICENSE
threads_arg/phase.py
threads_arg/map_mutations_to_arg.py
threads_arg/fwbw.py
threads_arg/convert.py
threads_arg/__init__.py
threads_arg/impute.py
threads_arg/threads_to_vcf.py
threads_arg/allele_ages.py
threads_arg/utils.py
threads_arg/infer.py
threads_arg/__main__.py
threads_arg/serialization.py
