Metadata-Version: 2.2
Name: threads-arg
Version: 0.2.1
Summary: Highly scalable inference of ancestral recombination graphs (ARGs)
Author: Threads Developers
Classifier: Development Status :: 4 - Beta
Classifier: License :: OSI Approved :: GNU General Public License v3 or later (GPLv3+)
Classifier: Programming Language :: Python :: 3 :: Only
Classifier: Programming Language :: Python :: 3.9
Classifier: Programming Language :: Python :: 3.10
Classifier: Programming Language :: Python :: 3.11
Classifier: Programming Language :: Python :: 3.12
Classifier: Programming Language :: Python :: 3.13
Requires-Python: >=3.9
Requires-Dist: click
Requires-Dist: xarray
Requires-Dist: h5py
Requires-Dist: pandas
Requires-Dist: numba
Requires-Dist: numpy
Requires-Dist: tszip
Requires-Dist: arg-needle-lib==1.1.3
Requires-Dist: cyvcf2
Requires-Dist: ray
Requires-Dist: pgenlib
Requires-Dist: tqdm
Provides-Extra: dev
Requires-Dist: pytest; extra == "dev"
